<?xml version="1.0" encoding="utf-8" standalone="yes"?>
<BarbarianCall>
  <Coordinate X="-1043.31" Y="162.42" Z="57.31">
    <Heading>31.224</Heading>
  </Coordinate>
  <Coordinate X="-460.6" Y="18.78" Z="45.31">
    <Heading>86.076</Heading>
  </Coordinate>
  <Coordinate X="762.86" Y="6515.31" Z="25.47">
    <Heading>78.153</Heading>
  </Coordinate>
  <Coordinate X="92.42" Y="6486.33" Z="31.11">
    <Heading>135.752</Heading>
  </Coordinate>
  <Coordinate X="-557.06" Y="477.21" Z="102.78">
    <Heading>200.26</Heading>
  </Coordinate>
  <Coordinate X="-236.33" Y="-1234.64" Z="36.88">
    <Heading>268.311</Heading>
  </Coordinate>
  <Coordinate X="-2605.47" Y="-120.15" Z="20.25">
    <Heading>44.833</Heading>
  </Coordinate>
  <Coordinate X="-433.05" Y="-803.74" Z="37.44">
    <Heading>175.736</Heading>
  </Coordinate>
  <Coordinate X="1064.72" Y="-851.72" Z="49.06">
    <Heading>271.04</Heading>
  </Coordinate>
  <Coordinate X="1877.38" Y="3954.86" Z="32.73">
    <Heading>93.558</Heading>
  </Coordinate>
  <Coordinate X="945.76" Y="2180.92" Z="48.35">
    <Heading>225.729</Heading>
  </Coordinate>
  <Coordinate X="-936.7" Y="-2141.15" Z="8.62">
    <Heading>314.522</Heading>
  </Coordinate>
  <Coordinate X="257.77" Y="2734.15" Z="43.68">
    <Heading>193.918</Heading>
  </Coordinate>
  <Coordinate X="-880.2" Y="-2262.26" Z="18.55">
    <Heading>134.259</Heading>
  </Coordinate>
  <Coordinate X="1833.64" Y="3890.63" Z="33.28">
    <Heading>109.562</Heading>
  </Coordinate>
  <Coordinate X="114.84" Y="3537.02" Z="39.48">
    <Heading>6.151</Heading>
  </Coordinate>
  <Coordinate X="1106.48" Y="1927.71" Z="60.92">
    <Heading>197.4</Heading>
  </Coordinate>
  <Coordinate X="1259.85" Y="-2151.7" Z="47.27">
    <Heading>204.128</Heading>
  </Coordinate>
  <Coordinate X="-3008.43" Y="365.82" Z="14.48">
    <Heading>169.582</Heading>
  </Coordinate>
  <Coordinate X="-171.58" Y="2854.91" Z="48.14">
    <Heading>248.832</Heading>
  </Coordinate>
  <Coordinate X="2371.45" Y="-680.8" Z="63.1">
    <Heading>91.696</Heading>
  </Coordinate>
  <Coordinate X="2366.56" Y="1081.05" Z="80.88">
    <Heading>42.485</Heading>
  </Coordinate>
  <Coordinate X="-618.16" Y="-1885.99" Z="29.26">
    <Heading>86.391</Heading>
  </Coordinate>
  <Coordinate X="1617.76" Y="-2542.45" Z="70.12">
    <Heading>278.771</Heading>
  </Coordinate>
  <Coordinate X="2722.72" Y="5123.94" Z="43.99">
    <Heading>56.367</Heading>
  </Coordinate>
  <Coordinate X="193.32" Y="1445.99" Z="239.66">
    <Heading>42.757</Heading>
  </Coordinate>
  <Coordinate X="2668.94" Y="3129.4" Z="50.36">
    <Heading>322.646</Heading>
  </Coordinate>
  <Coordinate X="496.26" Y="-885.53" Z="25.19">
    <Heading>180.726</Heading>
  </Coordinate>
  <Coordinate X="-378.49" Y="-1503.8" Z="34.07">
    <Heading>338.572</Heading>
  </Coordinate>
  <Coordinate X="1192.49" Y="-1645.58" Z="41.72">
    <Heading>304.056</Heading>
  </Coordinate>
  <Coordinate X="-1348.17" Y="2297.09" Z="41.57">
    <Heading>0.101</Heading>
  </Coordinate>
  <Coordinate X="-2054.26" Y="1967.31" Z="188.76">
    <Heading>153.941</Heading>
  </Coordinate>
  <Coordinate X="-2856.82" Y="2195.17" Z="33.04">
    <Heading>118.672</Heading>
  </Coordinate>
  <Coordinate X="-709.91" Y="-554.67" Z="32.3">
    <Heading>258.864</Heading>
  </Coordinate>
  <Coordinate X="-2526.43" Y="3528.1" Z="14.18">
    <Heading>156.614</Heading>
  </Coordinate>
  <Coordinate X="157.89" Y="3192.95" Z="41.91">
    <Heading>148.133</Heading>
  </Coordinate>
  <Coordinate X="-255.56" Y="6270.3" Z="31.02">
    <Heading>315.854</Heading>
  </Coordinate>
  <Coordinate X="1697.73" Y="2885.54" Z="43.45">
    <Heading>126.691</Heading>
  </Coordinate>
  <Coordinate X="34.59" Y="6395.49" Z="31.02">
    <Heading>314.524</Heading>
  </Coordinate>
  <Coordinate X="-803.29" Y="-2196.34" Z="16.51">
    <Heading>130.172</Heading>
  </Coordinate>
  <Coordinate X="650.48" Y="46.26" Z="86.22">
    <Heading>68.538</Heading>
  </Coordinate>
  <Coordinate X="1758.66" Y="3538.26" Z="35.78">
    <Heading>299.739</Heading>
  </Coordinate>
  <Coordinate X="924.53" Y="-126.71" Z="75.75">
    <Heading>59.527</Heading>
  </Coordinate>
  <Coordinate X="2206.06" Y="1267.12" Z="75.76">
    <Heading>40.168</Heading>
  </Coordinate>
  <Coordinate X="1370.08" Y="-1531.9" Z="55.63">
    <Heading>108.446</Heading>
  </Coordinate>
  <Coordinate X="-41.52" Y="-1723.46" Z="28.92">
    <Heading>294.653</Heading>
  </Coordinate>
  <Coordinate X="265.27" Y="-1560.08" Z="28.8">
    <Heading>301.641</Heading>
  </Coordinate>
  <Coordinate X="1976.39" Y="2987.12" Z="45.42">
    <Heading>100.552</Heading>
  </Coordinate>
  <Coordinate X="215.08" Y="3059.35" Z="41.99">
    <Heading>185.264</Heading>
  </Coordinate>
  <Coordinate X="1855.54" Y="3930.49" Z="32.77">
    <Heading>195.137</Heading>
  </Coordinate>
  <Coordinate X="1184.6" Y="-432.94" Z="66.73">
    <Heading>166.731</Heading>
  </Coordinate>
  <Coordinate X="1943.07" Y="3318.28" Z="45.04">
    <Heading>78.458</Heading>
  </Coordinate>
  <Coordinate X="2.47" Y="-484.9" Z="33.39">
    <Heading>89.768</Heading>
  </Coordinate>
  <Coordinate X="2145.75" Y="3268.61" Z="45.93">
    <Heading>68.51</Heading>
  </Coordinate>
  <Coordinate X="-825.94" Y="-1715.5" Z="32.81">
    <Heading>124.021</Heading>
  </Coordinate>
  <Coordinate X="2579.97" Y="2623.6" Z="36.76">
    <Heading>20.094</Heading>
  </Coordinate>
  <Coordinate X="-431.93" Y="-1048.45" Z="37.61">
    <Heading>168.326</Heading>
  </Coordinate>
  <Coordinate X="2627.77" Y="5005.9" Z="44.49">
    <Heading>197.413</Heading>
  </Coordinate>
  <Coordinate X="2342.41" Y="5074.98" Z="45.57">
    <Heading>315.297</Heading>
  </Coordinate>
  <Coordinate X="192.91" Y="432.23" Z="118.36">
    <Heading>103.419</Heading>
  </Coordinate>
  <Coordinate X="-1618.64" Y="-753.96" Z="11.21">
    <Heading>236.078</Heading>
  </Coordinate>
  <Coordinate X="1340.79" Y="-2591.35" Z="47.75">
    <Heading>285.769</Heading>
  </Coordinate>
  <Coordinate X="-807.75" Y="-1771.47" Z="33.36">
    <Heading>281.381</Heading>
  </Coordinate>
  <Coordinate X="1328.25" Y="2688.45" Z="37.42">
    <Heading>91.915</Heading>
  </Coordinate>
  <Coordinate X="-893.85" Y="2756.9" Z="23.47">
    <Heading>80.608</Heading>
  </Coordinate>
  <Coordinate X="-1144.1" Y="-680.96" Z="10.65">
    <Heading>302.137</Heading>
  </Coordinate>
  <Coordinate X="787.42" Y="-1891.6" Z="28.93">
    <Heading>165.177</Heading>
  </Coordinate>
  <Coordinate X="-189.71" Y="-1804.4" Z="29.52">
    <Heading>299.635</Heading>
  </Coordinate>
  <Coordinate X="-546.97" Y="204.54" Z="76.41">
    <Heading>176.545</Heading>
  </Coordinate>
  <Coordinate X="1158.74" Y="-2089.31" Z="41.72">
    <Heading>275.72</Heading>
  </Coordinate>
  <Coordinate X="981.77" Y="3638" Z="32.07">
    <Heading>88.339</Heading>
  </Coordinate>
  <Coordinate X="-693.57" Y="2814.18" Z="27.93">
    <Heading>301.694</Heading>
  </Coordinate>
  <Coordinate X="1937.85" Y="6235.57" Z="43.66">
    <Heading>201.969</Heading>
  </Coordinate>
  <Coordinate X="-266.66" Y="431.62" Z="107.89">
    <Heading>66.77</Heading>
  </Coordinate>
  <Coordinate X="23.76" Y="366.16" Z="112.26">
    <Heading>55.287</Heading>
  </Coordinate>
  <Coordinate X="-945.46" Y="-1816.57" Z="19.43">
    <Heading>316.798</Heading>
  </Coordinate>
  <Coordinate X="2743.59" Y="4691.75" Z="44.06">
    <Heading>12.734</Heading>
  </Coordinate>
  <Coordinate X="-653.14" Y="-600.57" Z="33.35">
    <Heading>174.237</Heading>
  </Coordinate>
  <Coordinate X="2476.99" Y="1296.13" Z="48.84">
    <Heading>329.646</Heading>
  </Coordinate>
  <Coordinate X="2516.15" Y="5553.15" Z="44.5">
    <Heading>21.368</Heading>
  </Coordinate>
  <Coordinate X="1169.42" Y="-1677.83" Z="35.9">
    <Heading>334.675</Heading>
  </Coordinate>
  <Coordinate X="1705.88" Y="-2048.77" Z="107.81">
    <Heading>170.794</Heading>
  </Coordinate>
  <Coordinate X="1235.42" Y="6501.71" Z="20.52">
    <Heading>89.031</Heading>
  </Coordinate>
  <Coordinate X="979.8" Y="520.42" Z="105.1">
    <Heading>77.706</Heading>
  </Coordinate>
  <Coordinate X="867.49" Y="-2239.34" Z="30.14">
    <Heading>85.823</Heading>
  </Coordinate>
  <Coordinate X="-413.63" Y="6024.99" Z="31.13">
    <Heading>196.181</Heading>
  </Coordinate>
  <Coordinate X="-76.75" Y="-1106.13" Z="25.67">
    <Heading>340.722</Heading>
  </Coordinate>
  <Coordinate X="1296.53" Y="-2602.94" Z="45.91">
    <Heading>275.605</Heading>
  </Coordinate>
  <Coordinate X="-926.9" Y="5429.04" Z="37.21">
    <Heading>106.777</Heading>
  </Coordinate>
  <Coordinate X="-3013.06" Y="1961.99" Z="29.35">
    <Heading>155.826</Heading>
  </Coordinate>
  <Coordinate X="-740.68" Y="-1878.98" Z="26.87">
    <Heading>196.6</Heading>
  </Coordinate>
  <Coordinate X="561.27" Y="2697.35" Z="41.79">
    <Heading>98.015</Heading>
  </Coordinate>
  <Coordinate X="1334" Y="-2578.03" Z="47.7">
    <Heading>103.063</Heading>
  </Coordinate>
  <Coordinate X="-743.34" Y="-2134.23" Z="13.48">
    <Heading>143.413</Heading>
  </Coordinate>
  <Coordinate X="1811.4" Y="3317.91" Z="41.93">
    <Heading>30.261</Heading>
  </Coordinate>
  <Coordinate X="645.87" Y="-609.17" Z="35.53">
    <Heading>242.261</Heading>
  </Coordinate>
  <Coordinate X="1367.14" Y="3679.2" Z="33.24">
    <Heading>109.774</Heading>
  </Coordinate>
  <Coordinate X="428.08" Y="-485.57" Z="35.54">
    <Heading>90.206</Heading>
  </Coordinate>
  <Coordinate X="-760.42" Y="-1158.5" Z="10.27">
    <Heading>216.71</Heading>
  </Coordinate>
  <Coordinate X="705.49" Y="3529.69" Z="33.91">
    <Heading>95.638</Heading>
  </Coordinate>
  <Coordinate X="-148.73" Y="-98.69" Z="54.64">
    <Heading>251.925</Heading>
  </Coordinate>
  <Coordinate X="-914.02" Y="2744.9" Z="23.98">
    <Heading>263.264</Heading>
  </Coordinate>
  <Coordinate X="-860.71" Y="357.53" Z="86.62">
    <Heading>185.438</Heading>
  </Coordinate>
  <Coordinate X="-470.76" Y="-2093.83" Z="27.1">
    <Heading>265.118</Heading>
  </Coordinate>
  <Coordinate X="-710.93" Y="1051.12" Z="246.22">
    <Heading>342.989</Heading>
  </Coordinate>
  <Coordinate X="26.29" Y="-812.05" Z="30.86">
    <Heading>326.553</Heading>
  </Coordinate>
  <Coordinate X="-421.34" Y="-1212.95" Z="54.56">
    <Heading>228.223</Heading>
  </Coordinate>
  <Coordinate X="-144.91" Y="6247.68" Z="30.94">
    <Heading>132.892</Heading>
  </Coordinate>
  <Coordinate X="-359.4" Y="-2112.9" Z="24.25">
    <Heading>259.519</Heading>
  </Coordinate>
  <Coordinate X="1944.65" Y="3861.01" Z="32.02">
    <Heading>296.656</Heading>
  </Coordinate>
  <Coordinate X="716.64" Y="335.19" Z="112.36">
    <Heading>260.783</Heading>
  </Coordinate>
  <Coordinate X="438.16" Y="-829.42" Z="28.19">
    <Heading>269.452</Heading>
  </Coordinate>
  <Coordinate X="1909.01" Y="3810.53" Z="32.08">
    <Heading>28.601</Heading>
  </Coordinate>
  <Coordinate X="144.93" Y="-587.39" Z="30.73">
    <Heading>251.867</Heading>
  </Coordinate>
  <Coordinate X="803.66" Y="-1502.2" Z="27.88">
    <Heading>205.544</Heading>
  </Coordinate>
  <Coordinate X="106.02" Y="-1735.67" Z="28.64">
    <Heading>230.662</Heading>
  </Coordinate>
  <Coordinate X="-1667.93" Y="2386.19" Z="34.04">
    <Heading>224.554</Heading>
  </Coordinate>
  <Coordinate X="-792.94" Y="439" Z="92.49">
    <Heading>278.313</Heading>
  </Coordinate>
  <Coordinate X="1653.71" Y="1174.29" Z="84.08">
    <Heading>344.168</Heading>
  </Coordinate>
  <Coordinate X="-439.02" Y="-1767.22" Z="20.17">
    <Heading>111.164</Heading>
  </Coordinate>
  <Coordinate X="-2020.67" Y="2332.11" Z="34.06">
    <Heading>292.223</Heading>
  </Coordinate>
  <Coordinate X="68.92" Y="-794" Z="31.28">
    <Heading>248.675</Heading>
  </Coordinate>
  <Coordinate X="2929.86" Y="3737.79" Z="52.38">
    <Heading>348.9</Heading>
  </Coordinate>
  <Coordinate X="82.1" Y="-676.79" Z="31.29">
    <Heading>340.55</Heading>
  </Coordinate>
  <Coordinate X="-1036.51" Y="250.37" Z="64.47">
    <Heading>270.457</Heading>
  </Coordinate>
  <Coordinate X="-661.06" Y="921.94" Z="229.37">
    <Heading>66.884</Heading>
  </Coordinate>
  <Coordinate X="-96.54" Y="-2161.34" Z="9.96">
    <Heading>291.884</Heading>
  </Coordinate>
  <Coordinate X="1207.81" Y="-1892.53" Z="36.36">
    <Heading>19.717</Heading>
  </Coordinate>
  <Coordinate X="1142.97" Y="-1856.37" Z="36.95">
    <Heading>288.838</Heading>
  </Coordinate>
  <Coordinate X="-493.25" Y="122.42" Z="63.28">
    <Heading>267.942</Heading>
  </Coordinate>
  <Coordinate X="1718.61" Y="-1771.21" Z="111.63">
    <Heading>157.225</Heading>
  </Coordinate>
  <Coordinate X="-1126.71" Y="-2002.12" Z="12.93">
    <Heading>230.196</Heading>
  </Coordinate>
  <Coordinate X="1047.3" Y="-1664.17" Z="30.81">
    <Heading>184.93</Heading>
  </Coordinate>
  <Coordinate X="638.92" Y="-1446.78" Z="30.11">
    <Heading>271.343</Heading>
  </Coordinate>
  <Coordinate X="-1542.16" Y="2217.34" Z="55.63">
    <Heading>176.639</Heading>
  </Coordinate>
  <Coordinate X="-2771.23" Y="1334.75" Z="78.33">
    <Heading>320.392</Heading>
  </Coordinate>
  <Coordinate X="423.52" Y="435.09" Z="141.38">
    <Heading>79.097</Heading>
  </Coordinate>
  <Coordinate X="2031.79" Y="2632.85" Z="53.04">
    <Heading>129.946</Heading>
  </Coordinate>
  <Coordinate X="-639.83" Y="496.33" Z="108.35">
    <Heading>281.525</Heading>
  </Coordinate>
  <Coordinate X="1143.31" Y="1828.5" Z="71.86">
    <Heading>212.931</Heading>
  </Coordinate>
  <Coordinate X="-1187.19" Y="-1344.4" Z="4.59">
    <Heading>118.222</Heading>
  </Coordinate>
  <Coordinate X="2048.56" Y="6072.65" Z="48.36">
    <Heading>230.514</Heading>
  </Coordinate>
  <Coordinate X="2359.25" Y="2816.87" Z="42.85">
    <Heading>293.365</Heading>
  </Coordinate>
  <Coordinate X="2457.42" Y="-176.68" Z="87.97">
    <Heading>334.014</Heading>
  </Coordinate>
  <Coordinate X="-245.86" Y="-474.45" Z="25.61">
    <Heading>82.181</Heading>
  </Coordinate>
  <Coordinate X="2723.75" Y="3295.1" Z="55.49">
    <Heading>154.188</Heading>
  </Coordinate>
  <Coordinate X="-1985.19" Y="-158.11" Z="30.35">
    <Heading>88.818</Heading>
  </Coordinate>
  <Coordinate X="1802.15" Y="-1551.67" Z="112.73">
    <Heading>327.237</Heading>
  </Coordinate>
  <Coordinate X="-3037.87" Y="1674.91" Z="34.88">
    <Heading>199.809</Heading>
  </Coordinate>
  <Coordinate X="-118.84" Y="-1944.85" Z="22.37">
    <Heading>51.444</Heading>
  </Coordinate>
  <Coordinate X="-579.02" Y="-248.54" Z="35.56">
    <Heading>29.596</Heading>
  </Coordinate>
  <Coordinate X="-440.13" Y="5942.58" Z="31.63">
    <Heading>139.498</Heading>
  </Coordinate>
  <Coordinate X="-698.39" Y="1181.56" Z="265.11">
    <Heading>310.282</Heading>
  </Coordinate>
  <Coordinate X="-2979.36" Y="416.71" Z="14.73">
    <Heading>356.147</Heading>
  </Coordinate>
  <Coordinate X="1169.6" Y="-1658.51" Z="36.6">
    <Heading>145.248</Heading>
  </Coordinate>
  <Coordinate X="839.68" Y="-1077.9" Z="27.52">
    <Heading>90.893</Heading>
  </Coordinate>
  <Coordinate X="-738.15" Y="-2448.97" Z="13.62">
    <Heading>152.331</Heading>
  </Coordinate>
  <Coordinate X="-2018.69" Y="2283.36" Z="46.61">
    <Heading>89.166</Heading>
  </Coordinate>
  <Coordinate X="-1389.06" Y="5107.08" Z="60.92">
    <Heading>121.706</Heading>
  </Coordinate>
  <Coordinate X="1721.11" Y="-2040.14" Z="108.67">
    <Heading>7.841</Heading>
  </Coordinate>
  <Coordinate X="2554.92" Y="297.39" Z="108.22">
    <Heading>179.788</Heading>
  </Coordinate>
  <Coordinate X="225.82" Y="3074.53" Z="41.95">
    <Heading>3.539</Heading>
  </Coordinate>
  <Coordinate X="-324.53" Y="6351.49" Z="30.07">
    <Heading>134.431</Heading>
  </Coordinate>
  <Coordinate X="-91.45" Y="293.66" Z="106.2">
    <Heading>244.574</Heading>
  </Coordinate>
  <Coordinate X="1284.94" Y="-622.3" Z="68.63">
    <Heading>34.444</Heading>
  </Coordinate>
  <Coordinate X="759.44" Y="-16.04" Z="81.57">
    <Heading>60.335</Heading>
  </Coordinate>
  <Coordinate X="1450.15" Y="-1506.83" Z="63.2">
    <Heading>90.159</Heading>
  </Coordinate>
  <Coordinate X="-1418.2" Y="2141.32" Z="52.89">
    <Heading>267.248</Heading>
  </Coordinate>
  <Coordinate X="1340.19" Y="-2394.29" Z="51.1">
    <Heading>352.447</Heading>
  </Coordinate>
  <Coordinate X="-2557.83" Y="1664.58" Z="144.33">
    <Heading>269.673</Heading>
  </Coordinate>
  <Coordinate X="-702.65" Y="-2150.33" Z="13.04">
    <Heading>309.856</Heading>
  </Coordinate>
  <Coordinate X="-269.76" Y="404.72" Z="109.76">
    <Heading>104.936</Heading>
  </Coordinate>
  <Coordinate X="1162" Y="-245.3" Z="68.76">
    <Heading>64.834</Heading>
  </Coordinate>
  <Coordinate X="-3078.42" Y="782.15" Z="19.59">
    <Heading>35.186</Heading>
  </Coordinate>
  <Coordinate X="1889.3" Y="1627.03" Z="80.88">
    <Heading>256.403</Heading>
  </Coordinate>
  <Coordinate X="-2165.06" Y="-277.45" Z="12.51">
    <Heading>159.793</Heading>
  </Coordinate>
  <Coordinate X="145.31" Y="-1796.09" Z="28.25">
    <Heading>139.333</Heading>
  </Coordinate>
  <Coordinate X="17.83" Y="-82.9" Z="59.33">
    <Heading>339.166</Heading>
  </Coordinate>
  <Coordinate X="1668.68" Y="-2381.11" Z="96.13">
    <Heading>298.716</Heading>
  </Coordinate>
  <Coordinate X="-22.25" Y="6633.13" Z="30.46">
    <Heading>123.217</Heading>
  </Coordinate>
  <Coordinate X="2866.91" Y="4425.02" Z="48.55">
    <Heading>289.185</Heading>
  </Coordinate>
  <Coordinate X="-2692.79" Y="2475.69" Z="16.44">
    <Heading>171.432</Heading>
  </Coordinate>
  <Coordinate X="1033.99" Y="-887.05" Z="30.4">
    <Heading>25.056</Heading>
  </Coordinate>
  <Coordinate X="-87.91" Y="1501.72" Z="283">
    <Heading>250.56</Heading>
  </Coordinate>
  <Coordinate X="2714.04" Y="4636.78" Z="44.33">
    <Heading>191.312</Heading>
  </Coordinate>
  <Coordinate X="-498" Y="-1247.72" Z="24.08">
    <Heading>158.814</Heading>
  </Coordinate>
  <Coordinate X="-1509.1" Y="-120.41" Z="51.79">
    <Heading>130.433</Heading>
  </Coordinate>
  <Coordinate X="-714.2" Y="-72.86" Z="37.33">
    <Heading>117.977</Heading>
  </Coordinate>
  <Coordinate X="2788.44" Y="4337.13" Z="49.62">
    <Heading>198.358</Heading>
  </Coordinate>
  <Coordinate X="1866.93" Y="-998.4" Z="78.7">
    <Heading>136.206</Heading>
  </Coordinate>
  <Coordinate X="1261.48" Y="-1590.46" Z="52.51">
    <Heading>127.264</Heading>
  </Coordinate>
  <Coordinate X="2291.46" Y="3112.24" Z="47.32">
    <Heading>21.113</Heading>
  </Coordinate>
  <Coordinate X="-1113.09" Y="-1519.23" Z="4.01">
    <Heading>308.183</Heading>
  </Coordinate>
  <Coordinate X="-2629.06" Y="2912.74" Z="16.45">
    <Heading>171.038</Heading>
  </Coordinate>
  <Coordinate X="-2331.08" Y="-286.41" Z="13.49">
    <Heading>48.307</Heading>
  </Coordinate>
  <Coordinate X="1288.31" Y="-1495.73" Z="39.34">
    <Heading>16.794</Heading>
  </Coordinate>
  <Coordinate X="41.53" Y="2834.89" Z="54.97">
    <Heading>287.006</Heading>
  </Coordinate>
  <Coordinate X="-515.42" Y="5834.35" Z="33.98">
    <Heading>149.464</Heading>
  </Coordinate>
  <Coordinate X="1477.52" Y="-1060.64" Z="55.4">
    <Heading>303.691</Heading>
  </Coordinate>
  <Coordinate X="-879.07" Y="239.94" Z="72.22">
    <Heading>64.384</Heading>
  </Coordinate>
  <Coordinate X="40.07" Y="-1357.18" Z="28.94">
    <Heading>91.367</Heading>
  </Coordinate>
  <Coordinate X="1088.71" Y="-1815.48" Z="36.4">
    <Heading>202.139</Heading>
  </Coordinate>
  <Coordinate X="-449.87" Y="2845.69" Z="35.05">
    <Heading>282.118</Heading>
  </Coordinate>
  <Coordinate X="1886.8" Y="2450.03" Z="54.31">
    <Heading>147.244</Heading>
  </Coordinate>
  <Coordinate X="-755.95" Y="155.75" Z="64.34">
    <Heading>187.746</Heading>
  </Coordinate>
  <Coordinate X="429.35" Y="2443.91" Z="45.91">
    <Heading>234.361</Heading>
  </Coordinate>
  <Coordinate X="-637.47" Y="-1387.1" Z="10.21">
    <Heading>357.103</Heading>
  </Coordinate>
  <Coordinate X="2177.7" Y="6065.31" Z="51.74">
    <Heading>66.284</Heading>
  </Coordinate>
  <Coordinate X="822.61" Y="-1660.16" Z="28.96">
    <Heading>174.221</Heading>
  </Coordinate>
  <Coordinate X="1624.4" Y="3826.88" Z="34.67">
    <Heading>128.799</Heading>
  </Coordinate>
  <Coordinate X="2547.16" Y="5309.49" Z="44.32">
    <Heading>194.032</Heading>
  </Coordinate>
  <Coordinate X="638.68" Y="261.78" Z="102.88">
    <Heading>333.697</Heading>
  </Coordinate>
  <Coordinate X="1725.01" Y="-1797.02" Z="110.53">
    <Heading>345.435</Heading>
  </Coordinate>
  <Coordinate X="-527.82" Y="-328.41" Z="34.79">
    <Heading>27.115</Heading>
  </Coordinate>
  <Coordinate X="232.55" Y="2896.31" Z="43.03">
    <Heading>188.528</Heading>
  </Coordinate>
  <Coordinate X="1699.29" Y="3683.17" Z="34.48">
    <Heading>28.743</Heading>
  </Coordinate>
  <Coordinate X="-1076.62" Y="-1604.21" Z="4.03">
    <Heading>218.696</Heading>
  </Coordinate>
  <Coordinate X="2418.44" Y="2943.76" Z="40.1">
    <Heading>127.708</Heading>
  </Coordinate>
  <Coordinate X="-1470.08" Y="-603.63" Z="30.5">
    <Heading>124.379</Heading>
  </Coordinate>
  <Coordinate X="-1678.78" Y="-500.34" Z="37.64">
    <Heading>322.766</Heading>
  </Coordinate>
  <Coordinate X="-43.94" Y="-1016.34" Z="28.57">
    <Heading>340.523</Heading>
  </Coordinate>
  <Coordinate X="1382.74" Y="-1761.45" Z="65.15">
    <Heading>108.434</Heading>
  </Coordinate>
  <Coordinate X="-833.06" Y="-77.55" Z="37.47">
    <Heading>118.392</Heading>
  </Coordinate>
  <Coordinate X="-1074.1" Y="-1381.39" Z="4.73">
    <Heading>346.939</Heading>
  </Coordinate>
  <Coordinate X="1512.54" Y="3740.26" Z="34.22">
    <Heading>118.229</Heading>
  </Coordinate>
  <Coordinate X="-852.88" Y="-2034.95" Z="27.47">
    <Heading>238.938</Heading>
  </Coordinate>
  <Coordinate X="1601.98" Y="-983.03" Z="60.76">
    <Heading>301.648</Heading>
  </Coordinate>
  <Coordinate X="-433.47" Y="347.8" Z="105.61">
    <Heading>278.556</Heading>
  </Coordinate>
  <Coordinate X="416.56" Y="3536.75" Z="33.76">
    <Heading>5.294</Heading>
  </Coordinate>
  <Coordinate X="1194.86" Y="1768.86" Z="76.97">
    <Heading>226.421</Heading>
  </Coordinate>
  <Coordinate X="846.74" Y="-2084.76" Z="29.71">
    <Heading>265.3</Heading>
  </Coordinate>
  <Coordinate X="1073.38" Y="-1288.43" Z="25.8">
    <Heading>2.674</Heading>
  </Coordinate>
  <Coordinate X="2106.87" Y="2628.42" Z="51.49">
    <Heading>314.321</Heading>
  </Coordinate>
  <Coordinate X="1215.45" Y="-1829.9" Z="37.89">
    <Heading>288.455</Heading>
  </Coordinate>
  <Coordinate X="311.26" Y="584.36" Z="154">
    <Heading>47.105</Heading>
  </Coordinate>
  <Coordinate X="2187.76" Y="4919.83" Z="40.51">
    <Heading>312.339</Heading>
  </Coordinate>
  <Coordinate X="-338.95" Y="-1471.68" Z="30.34">
    <Heading>180.078</Heading>
  </Coordinate>
  <Coordinate X="-2775.3" Y="40.15" Z="14.89">
    <Heading>66.977</Heading>
  </Coordinate>
  <Coordinate X="-131.32" Y="398.22" Z="112.91">
    <Heading>153.807</Heading>
  </Coordinate>
  <Coordinate X="-2659.95" Y="-95.22" Z="17.79">
    <Heading>223.328</Heading>
  </Coordinate>
  <Coordinate X="2074.57" Y="4687.26" Z="40.89">
    <Heading>309.469</Heading>
  </Coordinate>
  <Coordinate X="1091.75" Y="-1485.87" Z="28.16">
    <Heading>356.617</Heading>
  </Coordinate>
  <Coordinate X="-225.04" Y="3903.44" Z="37.16">
    <Heading>355.193</Heading>
  </Coordinate>
  <Coordinate X="839.42" Y="-648.55" Z="41.98">
    <Heading>56.421</Heading>
  </Coordinate>
  <Coordinate X="-721.74" Y="219.76" Z="77.38">
    <Heading>296.621</Heading>
  </Coordinate>
  <Coordinate X="-520.7" Y="6057.96" Z="25.11">
    <Heading>99.949</Heading>
  </Coordinate>
  <Coordinate X="382.21" Y="-1582.91" Z="28.92">
    <Heading>230.104</Heading>
  </Coordinate>
  <Coordinate X="1203.84" Y="643.53" Z="99.17">
    <Heading>325.704</Heading>
  </Coordinate>
  <Coordinate X="1722.22" Y="3733.64" Z="33.56">
    <Heading>300.195</Heading>
  </Coordinate>
  <Coordinate X="-732.83" Y="5531.09" Z="36.28">
    <Heading>120.771</Heading>
  </Coordinate>
  <Coordinate X="1199.62" Y="-461.67" Z="66.08">
    <Heading>345.359</Heading>
  </Coordinate>
  <Coordinate X="952.65" Y="6477.65" Z="20.82">
    <Heading>270.975</Heading>
  </Coordinate>
  <Coordinate X="1024.93" Y="1576.71" Z="170.14">
    <Heading>169.225</Heading>
  </Coordinate>
  <Coordinate X="2543.48" Y="14.71" Z="93.62">
    <Heading>341.987</Heading>
  </Coordinate>
  <Coordinate X="-18.05" Y="-1805.86" Z="26.59">
    <Heading>321.396</Heading>
  </Coordinate>
  <Coordinate X="1710.49" Y="1439.67" Z="85.19">
    <Heading>347.825</Heading>
  </Coordinate>
  <Coordinate X="1041.71" Y="-1201.16" Z="25.11">
    <Heading>183.217</Heading>
  </Coordinate>
  <Coordinate X="-419.8" Y="-672.01" Z="36.84">
    <Heading>178.309</Heading>
  </Coordinate>
  <Coordinate X="1208.23" Y="-1892.38" Z="36.31">
    <Heading>19.534</Heading>
  </Coordinate>
  <Coordinate X="-1192.29" Y="2588.54" Z="14.81">
    <Heading>309.276</Heading>
  </Coordinate>
  <Coordinate X="181.07" Y="-94.1" Z="66.97">
    <Heading>160.545</Heading>
  </Coordinate>
  <Coordinate X="2333.6" Y="2986.89" Z="47.71">
    <Heading>62.203</Heading>
  </Coordinate>
  <Coordinate X="-3135.38" Y="824.75" Z="16.52">
    <Heading>207.523</Heading>
  </Coordinate>
  <Coordinate X="-509.16" Y="-1950.44" Z="16.92">
    <Heading>319.748</Heading>
  </Coordinate>
  <Coordinate X="-389.36" Y="528.28" Z="121.47">
    <Heading>52.297</Heading>
  </Coordinate>
  <Coordinate X="-473.6" Y="-1863.58" Z="17.57">
    <Heading>104.854</Heading>
  </Coordinate>
  <Coordinate X="1636.95" Y="-2539.59" Z="72.7">
    <Heading>282.153</Heading>
  </Coordinate>
  <Coordinate X="-1369.16" Y="-867.07" Z="14.95">
    <Heading>136.66</Heading>
  </Coordinate>
  <Coordinate X="455.66" Y="-671.99" Z="27.57">
    <Heading>92.034</Heading>
  </Coordinate>
  <Coordinate X="-827.78" Y="-9.06" Z="40.31">
    <Heading>212.457</Heading>
  </Coordinate>
  <Coordinate X="-753.72" Y="-2445.96" Z="14.13">
    <Heading>329.583</Heading>
  </Coordinate>
  <Coordinate X="807.16" Y="-690.25" Z="41.3">
    <Heading>237.894</Heading>
  </Coordinate>
  <Coordinate X="-2007.75" Y="-458.9" Z="11.25">
    <Heading>228.652</Heading>
  </Coordinate>
  <Coordinate X="-156.01" Y="-2042.5" Z="22.52">
    <Heading>344.427</Heading>
  </Coordinate>
  <Coordinate X="1737" Y="-898.29" Z="69.21">
    <Heading>304.315</Heading>
  </Coordinate>
  <Coordinate X="1045.13" Y="-2393.99" Z="29.81">
    <Heading>353.378</Heading>
  </Coordinate>
  <Coordinate X="1661.09" Y="6412.98" Z="29.4">
    <Heading>70.849</Heading>
  </Coordinate>
  <Coordinate X="1779.35" Y="4565.43" Z="37.27">
    <Heading>271.978</Heading>
  </Coordinate>
  <Coordinate X="347.15" Y="2523.22" Z="44.35">
    <Heading>224.158</Heading>
  </Coordinate>
  <Coordinate X="-464.94" Y="767.38" Z="171.06">
    <Heading>358.82</Heading>
  </Coordinate>
  <Coordinate X="2532.45" Y="858.94" Z="87.1">
    <Heading>28.365</Heading>
  </Coordinate>
  <Coordinate X="1139.53" Y="-2579.5" Z="32.42">
    <Heading>285.431</Heading>
  </Coordinate>
  <Coordinate X="1831.23" Y="3707.38" Z="33.27">
    <Heading>299.654</Heading>
  </Coordinate>
  <Coordinate X="1682.3" Y="3620.8" Z="35.18">
    <Heading>300.132</Heading>
  </Coordinate>
  <Coordinate X="-570.42" Y="5714.4" Z="36.88">
    <Heading>153.919</Heading>
  </Coordinate>
  <Coordinate X="-1135.68" Y="-130.37" Z="38.7">
    <Heading>62.768</Heading>
  </Coordinate>
  <Coordinate X="417.32" Y="-1378.43" Z="29.43">
    <Heading>50.816</Heading>
  </Coordinate>
  <Coordinate X="2892.47" Y="3755.44" Z="52.36">
    <Heading>165.04</Heading>
  </Coordinate>
  <Coordinate X="2040.42" Y="1539.55" Z="75.11">
    <Heading>24.188</Heading>
  </Coordinate>
  <Coordinate X="-615.09" Y="252.82" Z="81.42">
    <Heading>265.427</Heading>
  </Coordinate>
  <Coordinate X="2161.59" Y="1269.75" Z="75.62">
    <Heading>209.084</Heading>
  </Coordinate>
  <Coordinate X="1164.26" Y="-1693.97" Z="35.12">
    <Heading>345.072</Heading>
  </Coordinate>
  <Coordinate X="2451.55" Y="5115.73" Z="46.65">
    <Heading>245.399</Heading>
  </Coordinate>
  <Coordinate X="24.73" Y="-1866.86" Z="22.87">
    <Heading>50.634</Heading>
  </Coordinate>
  <Coordinate X="1684.21" Y="-2372.74" Z="97.87">
    <Heading>309.577</Heading>
  </Coordinate>
  <Coordinate X="220.03" Y="3292.73" Z="40.61">
    <Heading>165.086</Heading>
  </Coordinate>
  <Coordinate X="908.06" Y="473.03" Z="120.67">
    <Heading>170.018</Heading>
  </Coordinate>
  <Coordinate X="-3100.05" Y="1110.85" Z="20.2">
    <Heading>354.335</Heading>
  </Coordinate>
  <Coordinate X="1116.18" Y="832.74" Z="152.19">
    <Heading>329.595</Heading>
  </Coordinate>
  <Coordinate X="-287.4" Y="-114.23" Z="45.51">
    <Heading>164.349</Heading>
  </Coordinate>
  <Coordinate X="-2175.74" Y="4444.23" Z="61.82">
    <Heading>141.529</Heading>
  </Coordinate>
  <Coordinate X="400.96" Y="-716.68" Z="28.92">
    <Heading>181.596</Heading>
  </Coordinate>
  <Coordinate X="-1431.83" Y="-504.62" Z="32.81">
    <Heading>214.644</Heading>
  </Coordinate>
  <Coordinate X="-91.42" Y="-1291.28" Z="28.9">
    <Heading>359.895</Heading>
  </Coordinate>
  <Coordinate X="-747.47" Y="-1596.62" Z="14.11">
    <Heading>315.626</Heading>
  </Coordinate>
  <Coordinate X="1159.06" Y="2689.67" Z="37.77">
    <Heading>87.023</Heading>
  </Coordinate>
  <Coordinate X="2610.82" Y="5066.2" Z="44.51">
    <Heading>193.833</Heading>
  </Coordinate>
  <Coordinate X="-41.34" Y="-1260.21" Z="35.55">
    <Heading>264.626</Heading>
  </Coordinate>
  <Coordinate X="2478.57" Y="5531.55" Z="44.46">
    <Heading>200.919</Heading>
  </Coordinate>
  <Coordinate X="518.35" Y="2377.18" Z="47.84">
    <Heading>235.369</Heading>
  </Coordinate>
  <Coordinate X="1293.32" Y="1119.31" Z="105.38">
    <Heading>184.422</Heading>
  </Coordinate>
  <Coordinate X="1301.16" Y="-2042.85" Z="44.55">
    <Heading>292.234</Heading>
  </Coordinate>
  <Coordinate X="547.94" Y="160.74" Z="99.13">
    <Heading>342.528</Heading>
  </Coordinate>
  <Coordinate X="-1475.63" Y="-300.28" Z="46.56">
    <Heading>222.783</Heading>
  </Coordinate>
  <Coordinate X="1526.31" Y="2771.44" Z="37.73">
    <Heading>125.797</Heading>
  </Coordinate>
  <Coordinate X="-1723.98" Y="-429.08" Z="43.21">
    <Heading>321.03</Heading>
  </Coordinate>
  <Coordinate X="86.8" Y="-1931.63" Z="20.39">
    <Heading>219.287</Heading>
  </Coordinate>
  <Coordinate X="-357.4" Y="-540.26" Z="24.87">
    <Heading>269.528</Heading>
  </Coordinate>
  <Coordinate X="1267.34" Y="6479.2" Z="20.24">
    <Heading>270.102</Heading>
  </Coordinate>
  <Coordinate X="569.67" Y="6532.06" Z="27.71">
    <Heading>255.421</Heading>
  </Coordinate>
  <Coordinate X="-1110.54" Y="-1510.28" Z="4.13">
    <Heading>124.926</Heading>
  </Coordinate>
  <Coordinate X="1584.2" Y="6392.31" Z="25.35">
    <Heading>248.434</Heading>
  </Coordinate>
  <Coordinate X="-431.41" Y="6111.87" Z="31.23">
    <Heading>148.248</Heading>
  </Coordinate>
  <Coordinate X="2105.21" Y="2734.13" Z="48.52">
    <Heading>307.012</Heading>
  </Coordinate>
  <Coordinate X="2663.32" Y="3226.96" Z="53.73">
    <Heading>181.811</Heading>
  </Coordinate>
  <Coordinate X="1543.27" Y="853.77" Z="77.21">
    <Heading>334.352</Heading>
  </Coordinate>
  <Coordinate X="369.66" Y="-187.07" Z="59.51">
    <Heading>162.757</Heading>
  </Coordinate>
  <Coordinate X="1865.89" Y="2959.89" Z="45.41">
    <Heading>105.597</Heading>
  </Coordinate>
  <Coordinate X="1760.48" Y="3720.32" Z="33.87">
    <Heading>210.413</Heading>
  </Coordinate>
  <Coordinate X="2545.4" Y="5085.06" Z="43.93">
    <Heading>285.183</Heading>
  </Coordinate>
  <Coordinate X="-480.7" Y="5889.04" Z="32.91">
    <Heading>145.429</Heading>
  </Coordinate>
  <Coordinate X="-918.36" Y="-33.06" Z="40.36">
    <Heading>39.542</Heading>
  </Coordinate>
  <Coordinate X="-395.82" Y="69.57" Z="57.91">
    <Heading>180.902</Heading>
  </Coordinate>
  <Coordinate X="-1427.38" Y="-405.66" Z="35.82">
    <Heading>121.778</Heading>
  </Coordinate>
  <Coordinate X="-427.77" Y="1408" Z="292.77">
    <Heading>317.82</Heading>
  </Coordinate>
  <Coordinate X="922.33" Y="3594.72" Z="32.87">
    <Heading>177.726</Heading>
  </Coordinate>
  <Coordinate X="1888.22" Y="-975.22" Z="78.61">
    <Heading>130.856</Heading>
  </Coordinate>
  <Coordinate X="-1278.62" Y="-991.3" Z="9.59">
    <Heading>195.925</Heading>
  </Coordinate>
  <Coordinate X="1659.53" Y="3585.02" Z="35.25">
    <Heading>28.279</Heading>
  </Coordinate>
  <Coordinate X="-1754.16" Y="2069.49" Z="119.86">
    <Heading>313.428</Heading>
  </Coordinate>
  <Coordinate X="1198.21" Y="653.22" Z="99.25">
    <Heading>146.468</Heading>
  </Coordinate>
  <Coordinate X="2659.48" Y="4882.21" Z="44.38">
    <Heading>194.898</Heading>
  </Coordinate>
  <Coordinate X="1374.23" Y="682.46" Z="79.24">
    <Heading>138.185</Heading>
  </Coordinate>
  <Coordinate X="-321.2" Y="-1841.53" Z="23.86">
    <Heading>257.824</Heading>
  </Coordinate>
  <Coordinate X="984.5" Y="-918.64" Z="30.39">
    <Heading>195.955</Heading>
  </Coordinate>
  <Coordinate X="-461.87" Y="-1455.76" Z="29.28">
    <Heading>183.411</Heading>
  </Coordinate>
  <Coordinate X="952.51" Y="-2468.92" Z="28.2">
    <Heading>266.878</Heading>
  </Coordinate>
  <Coordinate X="-665.46" Y="1303.3" Z="281.81">
    <Heading>343.307</Heading>
  </Coordinate>
  <Coordinate X="-2304.39" Y="1859.86" Z="182.1">
    <Heading>263.954</Heading>
  </Coordinate>
  <Coordinate X="2142.75" Y="2726.56" Z="48.01">
    <Heading>123.278</Heading>
  </Coordinate>
  <Coordinate X="-3169.63" Y="1244.34" Z="10.58">
    <Heading>353.652</Heading>
  </Coordinate>
  <Coordinate X="-921.18" Y="-67.8" Z="38.13">
    <Heading>205.178</Heading>
  </Coordinate>
  <Coordinate X="-20.38" Y="3610.76" Z="42.42">
    <Heading>88.884</Heading>
  </Coordinate>
  <Coordinate X="1281.81" Y="882.15" Z="105.5">
    <Heading>163.119</Heading>
  </Coordinate>
  <Coordinate X="543.44" Y="-861.55" Z="40.33">
    <Heading>270.097</Heading>
  </Coordinate>
  <Coordinate X="-356.27" Y="-1620.11" Z="19.33">
    <Heading>159.505</Heading>
  </Coordinate>
  <Coordinate X="1136.97" Y="665.89" Z="123.04">
    <Heading>146.651</Heading>
  </Coordinate>
  <Coordinate X="1945.67" Y="2437.18" Z="54.29">
    <Heading>330.621</Heading>
  </Coordinate>
  <Coordinate X="1201.12" Y="-1707" Z="35.55">
    <Heading>298.741</Heading>
  </Coordinate>
  <Coordinate X="385.77" Y="-624.66" Z="28.6">
    <Heading>330.431</Heading>
  </Coordinate>
  <Coordinate X="-671.05" Y="-118.96" Z="37.49">
    <Heading>207.261</Heading>
  </Coordinate>
  <Coordinate X="2582.86" Y="1646.84" Z="28.14">
    <Heading>90.176</Heading>
  </Coordinate>
  <Coordinate X="827.55" Y="2705.45" Z="40.18">
    <Heading>89.266</Heading>
  </Coordinate>
  <Coordinate X="1341.93" Y="611.7" Z="80.06">
    <Heading>310.609</Heading>
  </Coordinate>
  <Coordinate X="148.03" Y="-2667.43" Z="18.56">
    <Heading>261.944</Heading>
  </Coordinate>
  <Coordinate X="1891.21" Y="-1397.3" Z="135.4">
    <Heading>329.782</Heading>
  </Coordinate>
  <Coordinate X="970.18" Y="-1891.11" Z="30.72">
    <Heading>267.843</Heading>
  </Coordinate>
  <Coordinate X="253.31" Y="-568.23" Z="42.93">
    <Heading>160.041</Heading>
  </Coordinate>
  <Coordinate X="-2361.03" Y="4046.45" Z="30.04">
    <Heading>165.78</Heading>
  </Coordinate>
  <Coordinate X="2497.78" Y="-541.65" Z="67.87">
    <Heading>223.762</Heading>
  </Coordinate>
  <Coordinate X="184.4" Y="6574.21" Z="31.6">
    <Heading>110.566</Heading>
  </Coordinate>
  <Coordinate X="-462.69" Y="6074.68" Z="30.71">
    <Heading>105.121</Heading>
  </Coordinate>
  <Coordinate X="920.3" Y="-2137.56" Z="30.11">
    <Heading>174.958</Heading>
  </Coordinate>
  <Coordinate X="-256.88" Y="6189.93" Z="31.09">
    <Heading>42.207</Heading>
  </Coordinate>
  <Coordinate X="159.02" Y="2892.77" Z="47.59">
    <Heading>311.338</Heading>
  </Coordinate>
  <Coordinate X="-13.63" Y="-1355.01" Z="28.91">
    <Heading>89.381</Heading>
  </Coordinate>
  <Coordinate X="1968.46" Y="2524.65" Z="54.34">
    <Heading>323.672</Heading>
  </Coordinate>
  <Coordinate X="-834.86" Y="204.16" Z="73.75">
    <Heading>265.172</Heading>
  </Coordinate>
  <Coordinate X="-931.64" Y="-126.54" Z="37.34">
    <Heading>118.223</Heading>
  </Coordinate>
  <Coordinate X="-159.64" Y="6337.34" Z="31.22">
    <Heading>226.727</Heading>
  </Coordinate>
  <Coordinate X="909" Y="-2290.3" Z="30.3">
    <Heading>173.87</Heading>
  </Coordinate>
  <Coordinate X="1288.29" Y="-2130.83" Z="46.86">
    <Heading>19.573</Heading>
  </Coordinate>
  <Coordinate X="2547.54" Y="2103.62" Z="19.33">
    <Heading>355.737</Heading>
  </Coordinate>
  <Coordinate X="323.33" Y="-112.01" Z="67.93">
    <Heading>252.169</Heading>
  </Coordinate>
  <Coordinate X="1755.29" Y="3851.15" Z="34.22">
    <Heading>119.367</Heading>
  </Coordinate>
  <Coordinate X="1286.69" Y="1494" Z="98.06">
    <Heading>174.323</Heading>
  </Coordinate>
  <Coordinate X="1243.86" Y="3639.19" Z="33.15">
    <Heading>102.674</Heading>
  </Coordinate>
  <Coordinate X="93.38" Y="1385.05" Z="259.52">
    <Heading>267.182</Heading>
  </Coordinate>
  <Coordinate X="1675.31" Y="-2143.19" Z="107.23">
    <Heading>326.65</Heading>
  </Coordinate>
  <Coordinate X="1961.88" Y="-730.3" Z="88.62">
    <Heading>311.514</Heading>
  </Coordinate>
  <Coordinate X="-1642.61" Y="4871.64" Z="60.57">
    <Heading>132.107</Heading>
  </Coordinate>
  <Coordinate X="-535.16" Y="-1930.52" Z="16.95">
    <Heading>136.603</Heading>
  </Coordinate>
  <Coordinate X="-1775.33" Y="-664.71" Z="10.14">
    <Heading>228.826</Heading>
  </Coordinate>
  <Coordinate X="-769" Y="5650.88" Z="23.82">
    <Heading>340.96</Heading>
  </Coordinate>
  <Coordinate X="-657.9" Y="-1383.7" Z="10.27">
    <Heading>180.558</Heading>
  </Coordinate>
  <Coordinate X="-272.47" Y="6089.52" Z="30.98">
    <Heading>315.174</Heading>
  </Coordinate>
  <Coordinate X="2597.98" Y="401.21" Z="108.22">
    <Heading>323.939</Heading>
  </Coordinate>
  <Coordinate X="2848.05" Y="4180.65" Z="49.82">
    <Heading>199.432</Heading>
  </Coordinate>
  <Coordinate X="374.1" Y="1732.58" Z="239.47">
    <Heading>131.116</Heading>
  </Coordinate>
  <Coordinate X="2387.87" Y="5727.21" Z="45.27">
    <Heading>208.577</Heading>
  </Coordinate>
  <Coordinate X="-1401.57" Y="-779.12" Z="10.68">
    <Heading>278.501</Heading>
  </Coordinate>
  <Coordinate X="-2858.97" Y="47.31" Z="14.11">
    <Heading>251.264</Heading>
  </Coordinate>
  <Coordinate X="2725.75" Y="5086.91" Z="42.65">
    <Heading>188.737</Heading>
  </Coordinate>
  <Coordinate X="74.55" Y="-770.86" Z="31.34">
    <Heading>74.347</Heading>
  </Coordinate>
  <Coordinate X="454.81" Y="117.26" Z="98.7">
    <Heading>68.266</Heading>
  </Coordinate>
  <Coordinate X="-900.63" Y="-572.58" Z="32.09">
    <Heading>207.59</Heading>
  </Coordinate>
  <Coordinate X="-562.83" Y="-825.85" Z="26.81">
    <Heading>89.354</Heading>
  </Coordinate>
  <Coordinate X="-1198.2" Y="-965.62" Z="4.63">
    <Heading>120.18</Heading>
  </Coordinate>
  <Coordinate X="-1350.83" Y="-1022.87" Z="7.51">
    <Heading>206.752</Heading>
  </Coordinate>
  <Coordinate X="-1632.72" Y="70.97" Z="61.83">
    <Heading>236.557</Heading>
  </Coordinate>
  <Coordinate X="-1623.66" Y="153.06" Z="60.35">
    <Heading>113.719</Heading>
  </Coordinate>
  <Coordinate X="-567.2" Y="269.41" Z="82.51">
    <Heading>85.02</Heading>
  </Coordinate>
  <Coordinate X="-670.93" Y="-1566.72" Z="16.36">
    <Heading>326.117</Heading>
  </Coordinate>
  <Coordinate X="-566.98" Y="-1235.09" Z="14.53">
    <Heading>323.04</Heading>
  </Coordinate>
  <Coordinate X="-542.29" Y="-2196.83" Z="5.6">
    <Heading>318.344</Heading>
  </Coordinate>
  <Coordinate X="2120.21" Y="5230.99" Z="57.31">
    <Heading>99.231</Heading>
  </Coordinate>
  <Coordinate X="2198.43" Y="5207.15" Z="61.01">
    <Heading>245.88</Heading>
  </Coordinate>
  <Coordinate X="-530.18" Y="292.83" Z="82.51">
    <Heading>353.318</Heading>
  </Coordinate>
  <Coordinate X="-326.24" Y="-1194.55" Z="38.17">
    <Heading>89.051</Heading>
  </Coordinate>
  <Coordinate X="-1915.22" Y="182.01" Z="83.13">
    <Heading>217.287</Heading>
  </Coordinate>
  <Coordinate X="-1968.75" Y="440.75" Z="99.62">
    <Heading>15.608</Heading>
  </Coordinate>
  <Coordinate X="-1835.61" Y="731.27" Z="132.65">
    <Heading>302.073</Heading>
  </Coordinate>
  <Coordinate X="-1853.03" Y="806.48" Z="139.24">
    <Heading>131.432</Heading>
  </Coordinate>
  <Coordinate X="-1571.93" Y="956" Z="158.74">
    <Heading>243.63</Heading>
  </Coordinate>
  <Coordinate X="-1284.45" Y="841.46" Z="189.83">
    <Heading>152.028</Heading>
  </Coordinate>
  <Coordinate X="-1137.28" Y="1059.42" Z="207.76">
    <Heading>346.087</Heading>
  </Coordinate>
  <Coordinate X="-648.64" Y="985.97" Z="238.67">
    <Heading>261.12</Heading>
  </Coordinate>
  <Coordinate X="-790.06" Y="1305.95" Z="257.62">
    <Heading>22.43</Heading>
  </Coordinate>
  <Coordinate X="-705.3" Y="1748.52" Z="203.47">
    <Heading>238.117</Heading>
  </Coordinate>
  <Coordinate X="-404.93" Y="1892.11" Z="206.42">
    <Heading>202.361</Heading>
  </Coordinate>
  <Coordinate X="-134.21" Y="1977.56" Z="189.02">
    <Heading>122.304</Heading>
  </Coordinate>
  <Coordinate X="-25.09" Y="2013.24" Z="172.85">
    <Heading>300.143</Heading>
  </Coordinate>
  <Coordinate X="90.45" Y="2060.7" Z="148.45">
    <Heading>240.16</Heading>
  </Coordinate>
  <Coordinate X="202.28" Y="2109.3" Z="120">
    <Heading>83.574</Heading>
  </Coordinate>
  <Coordinate X="433.73" Y="2124.47" Z="90.03">
    <Heading>306.261</Heading>
  </Coordinate>
  <Coordinate X="600.65" Y="2188.91" Z="68.69">
    <Heading>88.438</Heading>
  </Coordinate>
  <Coordinate X="602.06" Y="2159.59" Z="68.75">
    <Heading>112.927</Heading>
  </Coordinate>
  <Coordinate X="756.81" Y="2273.6" Z="48.91">
    <Heading>73.943</Heading>
  </Coordinate>
  <Coordinate X="854.11" Y="-1632.08" Z="30.46">
    <Heading>356.216</Heading>
  </Coordinate>
  <Coordinate X="869.47" Y="-340.36" Z="60.93">
    <Heading>271.738</Heading>
  </Coordinate>
  <Coordinate X="1023.14" Y="-316.32" Z="66.7">
    <Heading>57.733</Heading>
  </Coordinate>
  <Coordinate X="1029.33" Y="-425.48" Z="65.06">
    <Heading>127.643</Heading>
  </Coordinate>
  <Coordinate X="455.17" Y="-563.73" Z="47.46">
    <Heading>263.309</Heading>
  </Coordinate>
  <Coordinate X="437.58" Y="-346.2" Z="47.01">
    <Heading>149.106</Heading>
  </Coordinate>
  <Coordinate X="669.12" Y="-109.57" Z="74.5">
    <Heading>238.035</Heading>
  </Coordinate>
  <Coordinate X="901.89" Y="307.05" Z="87.67">
    <Heading>135.693</Heading>
  </Coordinate>
  <Coordinate X="1071.49" Y="-457.01" Z="64.59">
    <Heading>167.754</Heading>
  </Coordinate>
  <Coordinate X="1797.25" Y="-1208.44" Z="82.98">
    <Heading>338.486</Heading>
  </Coordinate>
  <Coordinate X="2158.66" Y="-826.39" Z="75.19">
    <Heading>323.196</Heading>
  </Coordinate>
  <Coordinate X="37.5" Y="-542.91" Z="34.82">
    <Heading>88.247</Heading>
  </Coordinate>
  <Coordinate X="100.72" Y="-319.71" Z="45.28">
    <Heading>250.953</Heading>
  </Coordinate>
  <Coordinate X="985.56" Y="189.57" Z="80.26">
    <Heading>49.333</Heading>
  </Coordinate>
  <Coordinate X="944.96" Y="139.4" Z="80.26">
    <Heading>49.797</Heading>
  </Coordinate>
  <Coordinate X="-1043.61" Y="-2542.18" Z="13.38">
    <Heading>148.948</Heading>
  </Coordinate>
  <Coordinate X="-436.35" Y="-1124.7" Z="28.91">
    <Heading>255.946</Heading>
  </Coordinate>
  <Coordinate X="-572.79" Y="-992.62" Z="21.67">
    <Heading>0.148</Heading>
  </Coordinate>
  <Coordinate X="-512.06" Y="-926.67" Z="24.17">
    <Heading>330.756</Heading>
  </Coordinate>
  <Coordinate X="-476.29" Y="-575.13" Z="24.9">
    <Heading>89.636</Heading>
  </Coordinate>
  <Coordinate X="-849.36" Y="-2487.88" Z="13.32">
    <Heading>1.988</Heading>
  </Coordinate>
  <Coordinate X="1667.68" Y="4809.33" Z="41.22">
    <Heading>189.703</Heading>
  </Coordinate>
  <Coordinate X="1705.01" Y="4946.64" Z="41.69">
    <Heading>236.487</Heading>
  </Coordinate>
  <Coordinate X="1831.35" Y="5067.47" Z="56.52">
    <Heading>307.184</Heading>
  </Coordinate>
  <Coordinate X="2013.2" Y="5066.59" Z="41.33">
    <Heading>219.821</Heading>
  </Coordinate>
  <Coordinate X="2327.66" Y="4718.1" Z="35.67">
    <Heading>68.592</Heading>
  </Coordinate>
  <Coordinate X="1703.44" Y="4643.13" Z="42.99">
    <Heading>9.116</Heading>
  </Coordinate>
  <Coordinate X="1294.6" Y="4475.95" Z="61.75">
    <Heading>80.555</Heading>
  </Coordinate>
  <Coordinate X="879.11" Y="4463.08" Z="51.34">
    <Heading>234.355</Heading>
  </Coordinate>
  <Coordinate X="800.84" Y="4261" Z="55.66">
    <Heading>246.045</Heading>
  </Coordinate>
  <Coordinate X="485.77" Y="4336.04" Z="57.79">
    <Heading>177.927</Heading>
  </Coordinate>
  <Coordinate X="-62.24" Y="4399.89" Z="55.39">
    <Heading>161.828</Heading>
  </Coordinate>
  <Coordinate X="-222.34" Y="4171.8" Z="42.55">
    <Heading>162.33</Heading>
  </Coordinate>
  <Coordinate X="-2007" Y="4499.71" Z="56.5">
    <Heading>316.976</Heading>
  </Coordinate>
  <Coordinate X="-1889.89" Y="4640.82" Z="56.47">
    <Heading>132.411</Heading>
  </Coordinate>
  <Coordinate X="-1393.14" Y="5075.42" Z="60.55">
    <Heading>302.196</Heading>
  </Coordinate>
  <Coordinate X="-1202.54" Y="5245.77" Z="50.77">
    <Heading>275.132</Heading>
  </Coordinate>
  <Coordinate X="-458.21" Y="5880.89" Z="32.63">
    <Heading>324.045</Heading>
  </Coordinate>
  <Coordinate X="1145.63" Y="1393.07" Z="157.34">
    <Heading>208.969</Heading>
  </Coordinate>
  <Coordinate X="1193.64" Y="931.8" Z="147">
    <Heading>293.226</Heading>
  </Coordinate>
  <Coordinate X="973.89" Y="839.87" Z="202.03">
    <Heading>325.138</Heading>
  </Coordinate>
  <Coordinate X="840.07" Y="968.53" Z="240.17">
    <Heading>298.84</Heading>
  </Coordinate>
  <Coordinate X="660.86" Y="775.21" Z="204.76">
    <Heading>274.148</Heading>
  </Coordinate>
  <Coordinate X="506.79" Y="977" Z="207.74">
    <Heading>301.256</Heading>
  </Coordinate>
  <Coordinate X="417.09" Y="1130.98" Z="236.23">
    <Heading>205.074</Heading>
  </Coordinate>
  <Coordinate X="418.82" Y="1198.67" Z="248.52">
    <Heading>356.175</Heading>
  </Coordinate>
  <Coordinate X="402.33" Y="934.83" Z="201.95">
    <Heading>8.193</Heading>
  </Coordinate>
  <Coordinate X="140.93" Y="952" Z="210.02">
    <Heading>35.781</Heading>
  </Coordinate>
  <Coordinate X="-119.14" Y="1059.1" Z="227.67">
    <Heading>99.231</Heading>
  </Coordinate>
  <Coordinate X="-205.45" Y="1040.89" Z="233.3">
    <Heading>261.925</Heading>
  </Coordinate>
  <Coordinate X="-1773.43" Y="-504.14" Z="38.54">
    <Heading>42.981</Heading>
  </Coordinate>
  <Coordinate X="2228.29" Y="6037.79" Z="51.44">
    <Heading>49.839</Heading>
  </Coordinate>
</BarbarianCall>